verbs-0.4.1.dist-info/METADATA
verbs-0.4.1.dist-info/WHEEL
verbs-0.4.1.dist-info/license_files/LICENSE
verbs/types.py
verbs/abi.py
verbs/__init__.py
verbs/sim.py
verbs/utils.py
verbs/batch_runner.py
verbs/envs.pypy39-pp73-x86_64-linux-gnu.so
verbs-0.4.1.dist-info/RECORD
