Metadata-Version: 2.3
Name: verbs
Version: 0.4.1
Classifier: Development Status :: 4 - Beta
Classifier: Programming Language :: Python
Classifier: Programming Language :: Python :: 3.8
Classifier: Programming Language :: Python :: 3.9
Classifier: Programming Language :: Python :: 3.10
Classifier: Programming Language :: Python :: 3.11
Classifier: Programming Language :: Rust
Classifier: Programming Language :: Python :: Implementation :: CPython
Classifier: Programming Language :: Python :: Implementation :: PyPy
Requires-Dist: eth-utils >=2.3.1
Requires-Dist: eth-abi >=4.2.1
Requires-Dist: tqdm >=4.66.1
Requires-Dist: numpy >=1.26.2
Requires-Dist: eth-hash[pycryptodome] >=0.5.2
Requires-Dist: joblib >=1.3.2
Requires-Dist: py-solc-x >=2.0.2
Requires-Dist: pandas >=2.2.0
License-File: LICENSE
Summary: Ethereum ABM Library
Keywords: ethereum,agent-based modelling,simulation,defi
Author-email: Jordan <jordan@simtopia.ai>, Marc <marc@simtopia.ai>
Maintainer-email: Jordan <jordan@simtopia.ai>, Marc <marc@simtopia.ai>
Requires-Python: >=3.8
Project-URL: docs, https://simtopia.github.io/verbs/
Project-URL: documentation, https://simtopia.github.io/verbs/
Project-URL: source, https://github.com/simtopia/verbs
